momento/__init__.py
momento/auth/__init__.py
momento/auth/access_control/__init__.py
momento/auth/access_control/disposable_token_scope.py
momento/auth/access_control/disposable_token_scopes.py
momento/auth/access_control/permission_scope.py
momento/auth/access_control/permission_scopes.py
momento/auth/credential_provider.py
momento/auth/momento_endpoint_resolver.py
momento/auth_client.py
momento/auth_client_async.py
momento/cache_client.py
momento/cache_client_async.py
momento/common_data/__init__.py
momento/config/__init__.py
momento/config/auth_configuration.py
momento/config/auth_configurations.py
momento/config/configuration.py
momento/config/configurations.py
momento/config/middleware/__init__.py
momento/config/middleware/aio/__init__.py
momento/config/middleware/aio/middleware.py
momento/config/middleware/aio/middleware_metadata.py
momento/config/middleware/models.py
momento/config/middleware/synchronous/__init__.py
momento/config/middleware/synchronous/middleware.py
momento/config/middleware/synchronous/middleware_metadata.py
momento/config/topic_configuration.py
momento/config/topic_configurations.py
momento/config/transport/__init__.py
momento/config/transport/grpc_configuration.py
momento/config/transport/topic_grpc_configuration.py
momento/config/transport/topic_transport_strategy.py
momento/config/transport/transport_strategy.py
momento/errors/__init__.py
momento/errors/error_converter.py
momento/errors/error_details.py
momento/errors/exceptions.py
momento/internal/__init__.py
momento/internal/_utilities/__init__.py
momento/internal/_utilities/_channel_credentials.py
momento/internal/_utilities/_client_type.py
momento/internal/_utilities/_data_validation.py
momento/internal/_utilities/_grpc_channel_options.py
momento/internal/_utilities/_permissions.py
momento/internal/_utilities/_python_runtime_version.py
momento/internal/_utilities/_time.py
momento/internal/aio/__init__.py
momento/internal/aio/_add_header_client_interceptor.py
momento-1.28.0.dist-info/LICENSE
momento-1.28.0.dist-info/WHEEL
momento-1.28.0.dist-info/METADATA
momento-1.28.0.dist-info/RECORD
