Metadata-Version: 2.1
Name: momento
Version: 1.28.0
Summary: SDK for Momento
Home-page: https://gomomento.com
License: Apache-2.0
Keywords: Momento,caching,key-value store,serverless
Author: Momento
Author-email: hello@momentohq.com
Requires-Python: >=3.7,<4.0
Classifier: Development Status :: 5 - Production/Stable
Classifier: Environment :: Console
Classifier: Framework :: AsyncIO
Classifier: Intended Audience :: Developers
Classifier: License :: OSI Approved :: Apache Software License
Classifier: Natural Language :: English
Classifier: Operating System :: OS Independent
Classifier: Programming Language :: Python :: 3
Classifier: Programming Language :: Python :: 3.7
Classifier: Programming Language :: Python :: 3.8
Classifier: Programming Language :: Python :: 3.9
Classifier: Programming Language :: Python :: 3.10
Classifier: Programming Language :: Python :: 3.11
Classifier: Topic :: Internet
Classifier: Typing :: Typed
Requires-Dist: grpcio (>=1.46.0,<2.0.0) ; python_version < "3.13"
Requires-Dist: grpcio (>=1.66.2,<2.0.0) ; python_version >= "3.13"
Requires-Dist: momento-wire-types (>=0.119.4,<0.120.0)
Requires-Dist: pyjwt (>=2.4.0,<3.0.0)
Project-URL: Documentation, https://docs.momentohq.com/
Project-URL: Repository, https://github.com/momentohq/client-sdk-python
